{
  "bocaditos": [
    {
      "id": 1,
      "name": "Bocadito de Matrimonio",
      "precio": 2,
      "imagen": "./assest/bocadito3.webp",
      "descripcion": "Manzana acaramelda con diseño para novio"
    },
    {
      "id": 2,
      "name": "Bocaditos dulces variados",
      "precio": 0.8,
      "imagen": "./assest/bocadito4.jpg",
      "descripcion": "Alfajores rellenos de manjar, brownie de chocolate"
    },
    {
      "id": 3,
      "name": "Empanada dulce",
      "precio": 1,
      "imagen": "./assest/bocadito5.jpg",
      "descripcion": "Empanadas relleno de dulce al escoger por el cliente"
    },
    {
      "id": 4,
      "name": "Beso de moza",
      "precio": 1,
      "imagen": "./assest/bocadito6.jpg",
      "descripcion": "Hecho a base de chocolate y relleno de dulce de huevo, y base de galleta."
    },
    {
      "id": 5,
      "name": "Minis alfajores",
      "precio": 0.8,
      "imagen": "./assest/bocadito7.jpg",
      "descripcion": "Mini alfajores relleno con manjar blanco a base de leche"
    },
    {
      "id": 6,
      "name": "Chupetines en vaso",
      "precio": 1.5,
      "imagen": "./assest/bocadito8.jpg",
      "descripcion": "Chupetines de chocolate con vainilla"
    }
  ],
  "tortas": [
    {
      "id": 1,
      "name": "Bocadito de Matrimonio",
      "precio": 2,
      "imagen": "./assest/bocadito3.webp",
      "descripcion": "Manzana acaramelda con diseño para novio"
    },
    {
      "id": 2,
      "name": "Bocaditos dulces variados",
      "precio": 0.8,
      "imagen": "./assest/bocadito4.jpg",
      "descripcion": "Alfajores rellenos de manjar, brownie de chocolate"
    },
    {
      "id": 3,
      "name": "Empanada dulce",
      "precio": 1,
      "imagen": "./assest/bocadito5.jpg",
      "descripcion": "Empanadas relleno de dulce al escoger por el cliente"
    },
    {
      "id": 4,
      "name": "Beso de moza",
      "precio": 1,
      "imagen": "./assest/bocadito6.jpg",
      "descripcion": "Hecho a base de chocolate y relleno de dulce de huevo, y base de galleta."
    },
    {
      "id": 5,
      "name": "Minis alfajores",
      "precio": 0.8,
      "imagen": "./assest/bocadito7.jpg",
      "descripcion": "Mini alfajores relleno con manjar blanco a base de leche"
    },
    {
      "id": 6,
      "name": "Chupetines en vaso",
      "precio": 1.5,
      "imagen": "./assest/bocadito8.jpg",
      "descripcion": "Chupetines de chocolate con vainilla"
    }
  ]
}